Lab 3/CLA_3bit.v
module CLA_3bit (
  input  [2:0] C,     
  input  [2:0] D,     
  input        Cin,   
  output [2:0] RES,   
  output       Carry  
);
  wire [2:0] P, G;
  wire [2:0] Carry_internal; // Renamed internal carry wire

  // Generate and propagate signals
  assign P = C ^ D; 
  assign G = C & D; 

  // Carry signals
  assign Carry_internal[0] = Cin;
  assign Carry_internal[1] = G[0] | (P[0] & Carry_internal[0]);
  assign Carry_internal[2] = G[1] | (P[1] & Carry_internal[1]);

  // Final carry
  assign Carry = G[2] | (P[2] & Carry_internal[2]);

  // Sum
  assign RES = P ^ Carry_internal;
endmodule

Lab 3/CLA_15bit_top.v
module CLA_15bit_top (
  input  [14:0] A   ,
  input  [14:0] B   ,
  input         mode, // 0 --> addition , 1 --> subtraction
  output [14:0] S   ,
  output        Cout,
  output        OVF
);
  wire [14:0] B_mode;
  wire Cin = mode;
  wire [4:0] Carry;

  // An always block to handle B_mode
  reg [14:0] B_mode_reg;
  assign B_mode = B_mode_reg;

  always @(*) 
  begin
    if (mode == 1)
      B_mode_reg = ~B; // Flip B bits for subtraction
    else
      B_mode_reg = B;
  end

  // Five 3-bit CLA modules with updated port names
  CLA_3bit cla0 (.C(A[2:0]),   .D(B_mode[2:0]),   .Cin(Cin),      .RES(S[2:0]),   .Carry(Carry[0]));
  CLA_3bit cla1 (.C(A[5:3]),   .D(B_mode[5:3]),   .Cin(Carry[0]), .RES(S[5:3]),   .Carry(Carry[1]));
  CLA_3bit cla2 (.C(A[8:6]),   .D(B_mode[8:6]),   .Cin(Carry[1]), .RES(S[8:6]),   .Carry(Carry[2]));
  CLA_3bit cla3 (.C(A[11:9]),  .D(B_mode[11:9]),  .Cin(Carry[2]), .RES(S[11:9]),  .Carry(Carry[3]));
  CLA_3bit cla4 (.C(A[14:12]), .D(B_mode[14:12]), .Cin(Carry[3]), .RES(S[14:12]), .Carry(Carry[4]));

  // Final carry-out
  assign Cout = Carry[4];

  // Overflow detection: If the carry into the MSB != carry out of MSB
  assign OVF = (A[14] ^ S[14]) & (B_mode[14] ^ S[14]);

endmodule

Lab 3/CLA_15bit_tb.v
module CLA_15bit_tb ();
reg  signed [14:0] A, B; // Declare as signed for handling negative values
reg         mode;        // mode (add or subtract)
wire signed [14:0] S;    // Declare as signed for result
wire        Ovf;         // Overflow
wire        Cout;        // Carry-out

  CLA_15bit_top dut (A, B, mode, S, Cout, Ovf);

  initial begin
    // Save the waveform under this file.
    $dumpfile("CLA_15bit_top.vcd");

    // Get the variables from the module.
    $dumpvars(0, CLA_15bit_tb);

    $display("Simulation started.");

    A = 15'd0;  // Set all inputs to zero.
    B = 15'd0;
    mode = 1'd0;
    #10;     // Wait 10 time units.
    A = 15'd25;
    B = 15'd50;
    mode = 1'd0; // For addition
    #10;     // Wait 10 time units.
    A = 15'd30;
    B = 15'd100;
    mode = 1'd1; // For subtraction
    #10;     // Wait 10 time units.

    // Addition without a carry and with an overflow
    A = 15'd16383; 
    B = 15'd2; 
    mode = 1'd0; 
    #10;

    // Addition with a carry and without an overflow
    A = 15'd63; 
    B = 15'd63; 
    mode = 1'd0; 
    #10;

    // Addition with a carry and with an overflow
    A = 15'd16383; 
    B = 15'd1; 
    mode = 1'd0; 
    #10;

    // Subtraction without a carry and without an overflow
    A = 15'd30; 
    B = 15'd100; 
    mode = 1'd1; 
    #10;

    // Subtraction without a carry and with an overflow
    A = 15'd16383; 
    B = -15'd16384; 
    mode = 1'd1; 
    #10;

    // Subtraction with a carry and without an overflow
    A = 15'd63; 
    B = 15'd31; 
    mode = 1'd1; 
    #10;

    // Subtraction with a carry and with an overflow
    A = -15'd16384; 
    B = 15'd1; 
    mode = 1'd1; 
    #10;

    $display("Simulation finished.");
    $finish(); // Finish simulation.
  end
endmodule

Lab 3/CLA_15bit_top.vcd
$date
	Mon Nov 25 12:13:31 2024
$end
$version
	Icarus Verilog
$end
$timescale
	1s
$end
$scope module CLA_15bit_tb $end
$var wire 15 ! S [14:0] $end
$var wire 1 " Ovf $end
$var wire 1 # Cout $end
$var reg 15 $ A [14:0] $end
$var reg 15 % B [14:0] $end
$var reg 1 & mode $end
$scope module dut $end
$var wire 15 ' A [14:0] $end
$var wire 15 ( B [14:0] $end
$var wire 1 ) Cin $end
$var wire 1 " OVF $end
$var wire 1 & mode $end
$var wire 15 * S [14:0] $end
$var wire 1 # Cout $end
$var wire 5 + Carry [4:0] $end
$var wire 15 , B_mode [14:0] $end
$var reg 15 - B_mode_reg [14:0] $end
$scope module cla0 $end
$var wire 3 . C [2:0] $end
$var wire 1 / Carry $end
$var wire 1 ) Cin $end
$var wire 3 0 D [2:0] $end
$var wire 3 1 G [2:0] $end
$var wire 3 2 P [2:0] $end
$var wire 3 3 RES [2:0] $end
$var wire 3 4 Carry_internal [2:0] $end
$upscope $end
$scope module cla1 $end
$var wire 3 5 C [2:0] $end
$var wire 1 6 Carry $end
$var wire 1 7 Cin $end
$var wire 3 8 D [2:0] $end
$var wire 3 9 G [2:0] $end
$var wire 3 : P [2:0] $end
$var wire 3 ; RES [2:0] $end
$var wire 3 < Carry_internal [2:0] $end
$upscope $end
$scope module cla2 $end
$var wire 3 = C [2:0] $end
$var wire 1 > Carry $end
$var wire 1 ? Cin $end
$var wire 3 @ D [2:0] $end
$var wire 3 A G [2:0] $end
$var wire 3 B P [2:0] $end
$var wire 3 C RES [2:0] $end
$var wire 3 D Carry_internal [2:0] $end
$upscope $end
$scope module cla3 $end
$var wire 3 E C [2:0] $end
$var wire 1 F Carry $end
$var wire 1 G Cin $end
$var wire 3 H D [2:0] $end
$var wire 3 I G [2:0] $end
$var wire 3 J P [2:0] $end
$var wire 3 K RES [2:0] $end
$var wire 3 L Carry_internal [2:0] $end
$upscope $end
$scope module cla4 $end
$var wire 3 M C [2:0] $end
$var wire 1 N Carry $end
$var wire 1 O Cin $end
$var wire 3 P D [2:0] $end
$var wire 3 Q G [2:0] $end
$var wire 3 R P [2:0] $end
$var wire 3 S RES [2:0] $end
$var wire 3 T Carry_internal [2:0] $end
$upscope $end
$upscope $end
$upscope $end
$enddefinitions $end
#0
$dumpvars
b0 T
b0 S
b0 R
b0 Q
b0 P
0O
0N
b0 M
b0 L
b0 K
b0 J
b0 I
b0 H
0G
0F
b0 E
b0 D
b0 C
b0 B
b0 A
b0 @
0?
0>
b0 =
b0 <
b0 ;
b0 :
b0 9
b0 8
07
06
b0 5
b0 4
b0 3
b0 2
b0 1
b0 0
0/
b0 .
b0 -
b0 ,
b0 +
b0 *
0)
b0 (
b0 '
0&
b0 %
b0 $
0#
0"
b0 !
$end
#10
b1 C
b1 D
1?
b10 +
16
b100 <
b10 9
b11 3
b1001011 !
b1001011 *
b1 ;
b10 0
b110 8
b11 2
b101 :
b110010 ,
b110010 -
b1 .
b11 5
b110010 %
b110010 (
b11001 $
b11001 '
#20
1"
b111 T
1O
1F
b111 L
1G
1>
17
1/
1?
b111 <
b1111 +
16
b111 D
b100 4
b1 3
b0 ;
b0 C
b0 K
b100000000000001 !
b100000000000001 *
b100 S
b0 8
b101 2
b10 1
b111 :
b0 9
b111 B
b111 J
b11 R
b10 ,
b10 -
b111 .
b111 5
b111 =
b111 E
b11 M
b10 %
b10 (
b11111111111111 $
b11111111111111 '
#30
0"
0G
0O
b110 4
b1 D
0>
b0 L
b11 +
0F
b0 T
b110 3
b111 ;
b0 2
b111 1
b0 :
b111 9
b1 C
b0 K
b1111110 !
b1111110 *
b0 S
b111 0
b111 8
b0 B
b0 J
b0 R
b111111 ,
b111111 -
b0 =
b0 E
b0 M
b111111 %
b111111 (
b111111 $
b111111 '
#40
1"
b111 T
1O
1F
b111 L
1G
1>
17
1?
b110 4
1/
b111 <
b1111 +
16
b111 D
b0 3
b0 ;
b110 2
b1 1
b111 :
b0 9
b0 C
b0 K
b100000000000000 !
b100000000000000 *
b100 S
b1 0
b0 8
b111 B
b111 J
b11 R
b1 ,
b1 -
b111 =
b111 E
b11 M
b1 %
b1 (
b11111111111111 $
b11111111111111 '
#50
0#
0N
0?
0G
0O
06
b0 D
0>
b0 L
b1 +
0F
b0 T
0"
b11 9
b111 ;
b110 C
b111 K
b111 S
b11 0
b11 8
b110 @
b111 H
b111 P
b101 2
b10 1
b0 :
b110 B
b111 J
b111 R
b111111110111010 !
b111111110111010 *
b10 3
b111111110011011 ,
b111111110011011 -
b110 .
b11 5
b0 =
b0 E
b0 M
b111 4
1)
1&
b1100100 %
b1100100 (
b11110 $
b11110 '
#60
1?
16
1G
1O
1"
b111 D
1>
b111 L
b1111 +
1F
b111 T
b111 9
b111 3
b111 ;
b111 C
b111 K
b111111111111111 !
b111111111111111 *
b111 S
b111 0
b111 8
b111 @
b11 P
b0 2
b111 1
b0 :
b0 B
b111 A
b0 J
b111 I
b0 R
b11 Q
b11111111111111 ,
b11111111111111 -
b111 .
b111 5
b111 =
b111 E
b11 M
b100000000000000 %
b100000000000000 (
b11111111111111 $
b11111111111111 '
#70
1#
1N
17
b111 4
1/
b111 <
1G
1O
b0 3
b100 ;
0"
b111 D
1>
b111 L
b11111 +
1F
b111 T
b111 2
b0 1
b11 :
b100 9
b0 C
b0 K
b100000 !
b100000 *
b0 S
b0 0
b100 8
b111 P
b111 B
b0 A
b111 J
b0 I
b111 R
b0 Q
b111111111100000 ,
b111111111100000 -
b0 =
b0 E
b0 M
b11111 %
b11111 (
b111111 $
b111111 '
#80
b0 T
0O
0F
b111 K
b0 L
0G
0>
07
b111 C
b1 4
0/
b0 <
b0 D
0?
b10000 +
06
b111 3
b111 ;
b11111111111111 !
b11111111111111 *
b11 S
1"
b110 0
b111 8
b110 2
b111 :
b0 9
b11 R
b100 Q
b111111111111110 ,
b111111111111110 -
b0 .
b0 5
b100 M
b1 %
b1 (
b100000000000000 $
b100000000000000 '
